{
  "kind": "orro-engine-lock",
  "schema_version": "1.0",
  "witnessd": {
    "repository": "Moonweave-Systems/witnessd",
    "commit": "38ba0ca40d00fc33e79560299c3b7ca8a3f2733e",
    "version": "2.27.0",
    "ref_name": "v2.27.0"
  },
  "depone": {
    "repository": "Moonweave-Systems/Depone",
    "commit": "f067a05299f755fe6b3c4b86aace2aa8822cc711",
    "ref_name": "v0.2.10"
  },
  "boundary": {
    "approves_merge": false,
    "raises_assurance": false,
    "executes_commands": false,
    "verifies_evidence": false
  }
}
